LICENSE
MANIFEST.in
README.rst
setup.py
django_session_csrf_per_view.egg-info/PKG-INFO
django_session_csrf_per_view.egg-info/SOURCES.txt
django_session_csrf_per_view.egg-info/dependency_links.txt
django_session_csrf_per_view.egg-info/not-zip-safe
django_session_csrf_per_view.egg-info/requires.txt
django_session_csrf_per_view.egg-info/top_level.txt
session_csrf/__init__.py
session_csrf/conf.py
session_csrf/context_processors.py
session_csrf/decorators.py
session_csrf/middlewares.py
session_csrf/mixins.py
session_csrf/models.py
session_csrf/utils.py
session_csrf/migrations/0001_initial.py
session_csrf/migrations/0002_auto__add_field_token_for_view.py
session_csrf/migrations/__init__.py
session_csrf/templatetags/__init__.py
session_csrf/templatetags/jinja_session_csrf.py
session_csrf/templatetags/session_csrf.py
session_csrf/tests/__init__.py
session_csrf/tests/base.py
session_csrf/tests/test_decorators.py
session_csrf/tests/test_middlewares.py
session_csrf/tests/test_models.py
session_csrf/tests/test_templatetags.py
session_csrf/tests/test_utils.py