Metadata-Version: 1.1
Name: django-session-csrf-per-view
Version: 0.5.3
Summary: CSRF protection for Django without cookies.
Home-page: http://github.com/mozilla/django-session-csrf
Author: Vladimir Iakovlev
Author-email: nvbn.rm@gmail.com
License: BSD
Platform: UNKNOWN
Classifier: Development Status :: 4 - Beta
Classifier: Environment :: Web Environment
Classifier: Environment :: Web Environment :: Mozilla
Classifier: Framework :: Django
Classifier: Intended Audience :: Developers
Classifier: License :: OSI Approved :: BSD License
Classifier: Operating System :: OS Independent
Classifier: Programming Language :: Python
Classifier: Topic :: Software Development :: Libraries :: Python Modules
